README.rst
setup.py
nb/__init__.py
nb/nb.py
nb/utils.py
nb.egg-info/PKG-INFO
nb.egg-info/SOURCES.txt
nb.egg-info/dependency_links.txt
nb.egg-info/entry_points.txt
nb.egg-info/not-zip-safe
nb.egg-info/requires.txt
nb.egg-info/top_level.txt